rekog2json2mongo/__init__.py
rekog2json2mongo/base.py
rekog2json2mongo/compare.py
rekog2json2mongo-0.1.1.dist-info/DESCRIPTION.rst
rekog2json2mongo-0.1.1.dist-info/METADATA
rekog2json2mongo-0.1.1.dist-info/RECORD
rekog2json2mongo-0.1.1.dist-info/WHEEL
rekog2json2mongo-0.1.1.dist-info/entry_points.txt
rekog2json2mongo-0.1.1.dist-info/metadata.json
rekog2json2mongo-0.1.1.dist-info/top_level.txt
