Metadata-Version: 2.0
Name: rekog2json2mongo
Version: 0.1.1
Summary: call AWS rekognition api, pushing local images, saving api results to json as well as mongodb
Home-page: https://github.com/shichaoji/rekog2json2mongo
Author: Shichao(Richard) Ji
Author-email: jshichao@vt.edu
License: MIT
Download-URL: https://github.com/shichaoji/rekog2json2mongo/archive/0.1.tar.gz
Keywords: database,ETL,mongodb,rekognition
Platform: UNKNOWN
Classifier: License :: OSI Approved :: MIT License
Classifier: Programming Language :: Python :: 2
Requires-Dist: pymongo
Requires-Dist: boto3
